src/alu.v
module alu (
    input [7:0] operand1,
    input [7:0] operand2,
    input [2:0] operation,
    input enable,
    output reg [7:0] result
);
    always @(*) begin
        if (enable) begin
            case (operation)
                // Arithmetic 
                3'b011: result <= operand1 + operand2;
                3'b100: result <= operand1 - operand2;

                default: result <= 8'b00000000; // Ensure default is 0
            endcase
        end
    end  
endmodule

src/register.v
module register (
    input clk,
    input write_enable,
    input [3:0] read_reg1,
    // input [2:0] read_reg2,
    input [7:0] write_data,
    output reg [7:0] read_data1
    // output reg [7:0] read_data2
);
    // Register file: 8 registers of 8 bits each
    reg [7:0] reg_file [7:0];
    initial begin
        reg_file[0] = 8'h00; // Example initial values
        reg_file[1] = 8'h00;
        reg_file[2] = 8'h00;
        reg_file[3] = 8'h00;
        reg_file[4] = 8'h00;
        reg_file[5] = 8'h00;
        reg_file[6] = 8'h00;
        reg_file[7] = 8'h00;
    end

    always @(posedge clk) begin
        // Write operation
        // if (write_enable) begin
            reg_file[read_reg1] <= write_data;
        // end
    end

    always @(*) begin
        // Read operations (combinational logic)
        read_data1 = reg_file[read_reg1];
        // read_data2 = reg_file[read_reg2];
    end
endmodule

src/memory.v
module memory (
    input wire clk,
    input wire write_enable,  // Write enable
    input wire [7:0] addr,    // Address for read/write
    input wire [7:0] data_in, // Data to write
    output reg [7:0] data_out // Data to read
);
    // Define the memory as an array of 256 8-bit registers
    reg [7:0] mem [255:0];
        integer i;
        initial begin
            for (i = 0; i < 256; i = i + 1) begin
                mem[i] = 8'b00000000; // Initialize with zero
            end
        end

    initial begin
        data_out = 8'b00000000; // Default value
    end 

    always @(*) begin
         // Default value
        if (write_enable) begin
            // Write operation
            mem[addr] <= data_in;
        end else begin
            // Read operation
            data_out <= mem[addr];
        end
    end

endmodule

src/cpu.v
module cpu (
    input wire clk,              // Clock signal
    input wire reset,            // Reset signal
    input wire [15:0] instr,     // Input instruction (16 bits)
    output reg [7:0] result      // Final output result
);
    wire [7:0] operand1;         // Operand1 for ALU
    reg [7:0] operand2;          // Operand2 for ALU
    wire [7:0] alu_result;       // ALU result (from alu module)
    reg [2:0] alu_op;            // ALU operation code
    reg [3:0] dest_reg;          // Destination register address
    reg [7:0] reg_write_data;    // Data to write to register
    reg [7:0] addr;              // Memory address
    reg write_enable;            // Register write enable
    wire [7:0] data_out;        // Data output from memory

    
    memory mem_inst (
        .clk(clk),
        .write_enable(write_enable),
        .addr(addr),
        .data_in(reg_write_data),
        .data_out(data_out)
    );

    // Register file instantiation
    register reg_file (
        .clk(clk),
        .write_enable(write_enable),
        .read_reg1(dest_reg),    // Read register 1 (based on instruction)
        .write_data(reg_write_data),
        .read_data1(operand1)
    );

    // ALU instantiation
    alu alu_inst (
        .operand1(operand1),
        .operand2(operand2),
        .operation(alu_op),
        .enable(1'b1),            // Always enabled
        .result(alu_result)
    );

    // Always block for combinational logic
    always @(*) begin
        alu_op = instr[14:12];   // Extract ALU operation from instruction
        
    end

    // Sequential logic
    always @(posedge clk or posedge reset) begin
        if (reset) begin
            result <= 8'b0;
            write_enable <= 0;
        end else begin
            case (alu_op)
                3'b000: begin // Immediate load to Register
                    write_enable <= 1;
                    dest_reg <= instr[11:8]; 
                    reg_write_data <= instr[7:0];
                end

                3'b001: begin // Register to memory
                    write_enable <= 1;
                    addr <= instr[7:0];
                    dest_reg <= instr[11:8];
                    reg_write_data <= operand1;
                end

                3'b010: begin // Memory read operation
                    write_enable <= 0;         // Ensure memory is in read mode
                    addr <= instr[7:0];        // Set the address
                    result <= data_out;  
                    dest_reg <= instr[11:8];
                    reg_write_data <=data_out;    // Store the memory output
                end

                3'b011: begin // ALU + operation
                    write_enable <= 1;
                    dest_reg <= instr[11:8]; 
                    operand2 <=instr[7:0];
                    result <= alu_result;
                    operand2 = instr[7:0];   // Operand2 comes from the immediate value
                    reg_write_data <=alu_result;
                end

                default: begin
                    write_enable <= 0;
                end
            endcase
        end
    end
endmodule

testbench/cpu_tb.v
module tb_cpu;

    // Testbench signals
    reg clk;
    reg reset;
    reg [15:0] instr;
    wire [7:0] result;

    initial begin
        $dumpfile("cpu.vcd");
        $dumpvars();
    end

    // Instantiate the CPU
    cpu uut (
        .clk(clk),
        .reset(reset),
        .instr(instr),
        .result(result)
    );

    // Clock generation
    always #5 clk = ~clk;

    // Test procedure
    initial begin
        // Initialize signals
        clk = 0;
        reset = 0;
        instr = 16'b0;

        // Apply reset
        reset = 1;
        #5;
        reset = 0;
        #5;
        
        // Cycle 1: Immediate Load to Register
        instr = 16'b0000_0000_00000100; // Load value 4 into register 0
        #20;
        instr = 16'b0001_0000_00000010; // write to memory at address 2
        #20;
        instr = 16'b0010_0001_00000010; // read from memory at address 2
        #20;
        instr = 16'b0011_0001_00000111; // add 7 with register 1
        #20;
        $display("Result: %b", result);

        // $display("Result: %b", result);

        // End simulation
        $stop;
    end

endmodule

src/program_counter.v
module program_counter (
    input wire clk,              // Clock signal
    input wire reset,            // Reset signal
    input enable,
    output reg [7:0] pc          // Current program counter value
);

    initial begin
        pc = 8'b00000000; // Initial value of the program counter
    end
   
    always @(posedge clk or posedge reset) begin
        if (reset) begin
            pc <= pc+1; // Reset the PC to 0
        end
    end
    always @(posedge reset) begin
        pc<=0;
    end

endmodule

cpu.vcd
$date
	Fri Aug 30 10:59:01 2024
$end
$version
	Icarus Verilog
$end
$timescale
	1s
$end
$scope module program_counter $end
$var wire 1 ! clk $end
$var wire 1 " enable $end
$var wire 1 # reset $end
$var reg 8 $ pc [7:0] $end
$upscope $end
$scope module tb_cpu $end
$var wire 8 % result [7:0] $end
$var reg 1 & clk $end
$var reg 16 ' instr [15:0] $end
$var reg 1 ( reset $end
$scope module uut $end
$var wire 1 & clk $end
$var wire 16 ) instr [15:0] $end
$var wire 1 ( reset $end
$var wire 8 * operand1 [7:0] $end
$var wire 8 + data_out [7:0] $end
$var wire 8 , alu_result [7:0] $end
$var reg 8 - addr [7:0] $end
$var reg 3 . alu_op [2:0] $end
$var reg 4 / dest_reg [3:0] $end
$var reg 8 0 operand2 [7:0] $end
$var reg 8 1 reg_write_data [7:0] $end
$var reg 8 2 result [7:0] $end
$var reg 1 3 write_enable $end
$scope module alu_inst $end
$var wire 1 4 enable $end
$var wire 8 5 operand2 [7:0] $end
$var wire 3 6 operation [2:0] $end
$var wire 8 7 operand1 [7:0] $end
$var reg 8 8 result [7:0] $end
$upscope $end
$scope module mem_inst $end
$var wire 8 9 addr [7:0] $end
$var wire 1 & clk $end
$var wire 8 : data_in [7:0] $end
$var wire 1 3 write_enable $end
$var reg 8 ; data_out [7:0] $end
$var integer 32 < i [31:0] $end
$upscope $end
$scope module reg_file $end
$var wire 1 & clk $end
$var wire 4 = read_reg1 [3:0] $end
$var wire 8 > write_data [7:0] $end
$var wire 1 3 write_enable $end
$var reg 8 ? read_data1 [7:0] $end
$upscope $end
$upscope $end
$upscope $end
$enddefinitions $end
#0
$dumpvars
bx ?
bx >
bx =
b100000000 <
bx ;
bx :
bx 9
b0 8
bx 7
b0 6
bx 5
14
03
b0 2
bx 1
bx 0
bx /
b0 .
bx -
b0 ,
bx +
bx *
b0 )
1(
b0 '
0&
b0 %
bx $
z#
z"
z!
$end
#5
b0 *
b0 7
b0 ?
b0 1
b0 :
b0 >
b0 /
b0 =
13
0(
1&
#10
b100 '
b100 )
0&
#15
b100 1
b100 :
b100 >
1&
#20
0&
#25
b100 *
b100 7
b100 ?
1&
#30
b1 .
b1 6
0&
b1000000000010 '
b1000000000010 )
#35
b10 -
b10 9
1&
#40
0&
#45
1&
#50
b10 .
b10 6
0&
b10000100000010 '
b10000100000010 )
#55
b100 +
b100 ;
b0 *
b0 7
b0 ?
bx 1
bx :
bx >
b1 /
b1 =
bx %
bx 2
03
1&
#60
0&
#65
bx *
bx 7
bx ?
b100 1
b100 :
b100 >
b100 %
b100 2
1&
#70
bx ,
bx 8
b11 .
b11 6
0&
b11000100000111 '
b11000100000111 )
#75
b1011 ,
b1011 8
b100 *
b100 7
b100 ?
bx 1
bx :
bx >
bx %
bx 2
13
b111 0
b111 5
1&
#80
0&
#85
bx ,
bx 8
bx *
bx 7
bx ?
b1011 1
b1011 :
b1011 >
b1011 %
b1011 2
1&
